svise/__init__.py
svise/extern/fastgl/LICENSE
svise/extern/fastgl/__init__.py
svise/extern/fastgl/fastgl.py
svise/extern/fastgl/fastgl.sh
svise/extern/fastgl/fastgl.txt
svise/extern/gpytorch_fit.py
svise/extern/quad_benchmarks/__init__.py
svise/extern/quad_benchmarks/genz.py
svise/extern/sindy_fit.py
svise/kernels/__init__.py
svise/kernels/_matern_kernel.py
svise/kernels/_squared_exp_kernel.py
svise/kernels/_utils.py
svise/odes/__init__.py
svise/odes/_odes.py
svise/pca/__init__.py
svise/pca/_pca.py
svise/quadrature/__init__.py
svise/quadrature/_barycentric_interp.py
svise/quadrature/_quadrature.py
svise/quadrature/_unbiased_quadrature.py
svise/sde_learning/__init__.py
svise/sde_learning/_diffusion_prior.py
svise/sde_learning/_likelihood.py
svise/sde_learning/_marginal_sde.py
svise/sde_learning/_sde_learner.py
svise/sde_learning/_sde_prior.py
svise/sdeint.py
svise/utils.py
svise/variationalsparsebayes/__init__.py
svise/variationalsparsebayes/sparse_bnn.py
svise/variationalsparsebayes/sparse_glm.py
svise/variationalsparsebayes/svi_half_cauchy.py
svise-0.1.4.dist-info/LICENSE
svise-0.1.4.dist-info/METADATA
svise-0.1.4.dist-info/WHEEL
svise-0.1.4.dist-info/RECORD
