Metadata-Version: 2.1
Name: svise
Version: 0.1.4
Summary: State estimation of a physical system with unknown governing equations
License: GNUv3
Author: coursekevin
Author-email: kevin.course@mail.utoronto.ca
Requires-Python: >=3.10,<4.0
Classifier: License :: Other/Proprietary License
Classifier: Programming Language :: Python :: 3
Classifier: Programming Language :: Python :: 3.10
Classifier: Programming Language :: Python :: 3.11
Classifier: Programming Language :: Python :: 3.12
Requires-Dist: botorch (>=0.8.5,<0.9.0)
Requires-Dist: gpytorch (>=1.10,<2.0)
Requires-Dist: scikit-learn (>=1.2.2,<2.0.0)
Requires-Dist: torch (>=2.0.1,<2.3.0)
Requires-Dist: torchsde (>=0.2.5,<0.3.0)
